elasticsearch_mcp/__init__.py
elasticsearch_mcp/config.py
elasticsearch_mcp/connection.py
elasticsearch_mcp/server.py
elasticsearch_mcp/auth/__init__.py
elasticsearch_mcp/auth/idp/__init__.py
elasticsearch_mcp/resources/__init__.py
elasticsearch_mcp/tools/__init__.py
elasticsearch_mcp/tools/cluster.py
elasticsearch_mcp/tools/indices.py
elasticsearch_mcp/tools/search.py
elasticsearch_mcp/utils/__init__.py
elasticsearch_mcp-0.1.1.dist-info/METADATA
elasticsearch_mcp-0.1.1.dist-info/WHEEL
elasticsearch_mcp-0.1.1.dist-info/entry_points.txt
elasticsearch_mcp-0.1.1.dist-info/licenses/LICENSE
elasticsearch_mcp-0.1.1.dist-info/RECORD
