Metadata-Version: 2.4
Name: elasticsearch-mcp
Version: 0.1.1
Summary: MCP server for Elasticsearch clusters
Project-URL: Homepage, https://github.com/bpamiri/elasticsearch-mcp
Project-URL: Repository, https://github.com/bpamiri/elasticsearch-mcp
Project-URL: Issues, https://github.com/bpamiri/elasticsearch-mcp/issues
Author-email: Peter <peter@example.com>
License-Expression: Apache-2.0
License-File: LICENSE
Keywords: ai,database,elasticsearch,mcp,search
Classifier: Development Status :: 3 - Alpha
Classifier: Intended Audience :: Developers
Classifier: License :: OSI Approved :: Apache Software License
Classifier: Programming Language :: Python :: 3
Classifier: Programming Language :: Python :: 3.10
Classifier: Programming Language :: Python :: 3.11
Classifier: Programming Language :: Python :: 3.12
Requires-Python: >=3.10
Requires-Dist: elasticsearch>=8.0.0
Requires-Dist: httpx>=0.25.0
Requires-Dist: mcp>=1.0.0
Requires-Dist: pydantic-settings>=2.0.0
Requires-Dist: uvicorn>=0.24.0
Provides-Extra: dev
Requires-Dist: mypy>=1.0.0; extra == 'dev'
Requires-Dist: pytest-asyncio>=0.21.0; extra == 'dev'
Requires-Dist: pytest-cov>=4.0.0; extra == 'dev'
Requires-Dist: pytest-mock>=3.10.0; extra == 'dev'
Requires-Dist: pytest>=7.0.0; extra == 'dev'
Requires-Dist: ruff>=0.1.0; extra == 'dev'
